um80/__init__.py
um80/opcodes_8080.py
um80/opcodes_z80.py
um80/relformat.py
um80/ucref80.py
um80/ud80.py
um80/ul80.py
um80/ulib80.py
um80/um80.py
um80/ux80.py
um80-0.3.34.dist-info/licenses/LICENSE
um80-0.3.34.dist-info/METADATA
um80-0.3.34.dist-info/WHEEL
um80-0.3.34.dist-info/entry_points.txt
um80-0.3.34.dist-info/top_level.txt
um80-0.3.34.dist-info/RECORD
