Metadata-Version: 2.4
Name: um80
Version: 0.3.34
Summary: Microsoft MACRO-80 compatible assembler toolchain for Linux
Author: um80 developers
License-Expression: GPL-3.0-or-later
Project-URL: Homepage, https://github.com/avwohl/um80_and_friends
Project-URL: Documentation, https://github.com/avwohl/um80_and_friends#readme
Project-URL: Repository, https://github.com/avwohl/um80_and_friends
Project-URL: Issues, https://github.com/avwohl/um80_and_friends/issues
Keywords: assembler,8080,z80,cp/m,macro-80,m80,l80,retro-computing,disassembler,linker,translator
Classifier: Development Status :: 4 - Beta
Classifier: Environment :: Console
Classifier: Intended Audience :: Developers
Classifier: Operating System :: POSIX :: Linux
Classifier: Operating System :: MacOS
Classifier: Programming Language :: Python :: 3
Classifier: Programming Language :: Python :: 3.8
Classifier: Programming Language :: Python :: 3.9
Classifier: Programming Language :: Python :: 3.10
Classifier: Programming Language :: Python :: 3.11
Classifier: Programming Language :: Python :: 3.12
Classifier: Programming Language :: Python :: 3.13
Classifier: Topic :: Software Development :: Assemblers
Classifier: Topic :: Software Development :: Build Tools
Classifier: Topic :: System :: Emulators
Requires-Python: >=3.8
License-File: LICENSE
Provides-Extra: dev
Requires-Dist: pytest>=7.0; extra == "dev"
Requires-Dist: pytest-cov; extra == "dev"
Requires-Dist: black; extra == "dev"
Requires-Dist: mypy; extra == "dev"
Dynamic: license-file
